{
  "Id": "Gender_Lookup",
  "Method": "DefaultRepo.BaseInfo.ReadList",
  "Inputs": {
    "ClientQueryJE": {
      "QueryFullName": "DefaultRepo.BaseInfo.ReadList",
    	"Where": {
    		"CompareClauses": [
    			{
    				"Name": "ParentId",
    				"Value": 10000,
    				"ClauseOperator": "Equal"
    			}
    		]
    	},
      "OrderClauses": [
        {
          "Name": "ViewOrder",
          "OrderDirection": "ASC"
        }
      ],
      "Pagination": {
        "PageNumber": 1,
        "PageSize": 500
      },
      "IncludeSubQueries": false
    }
  }
}