{"DefaultRepo.BaseActivityLog.ReadList":{"AccessRules":{"AllowedRoles":[],"AllowedUsers":[],"DeniedUsers":[]},"CachePolicy":{"CacheLevel":"None","AbsoluteExpirationSeconds":0},"LogPolicy":"IgnoreLogging"},"DefaultRepo.BaseActivityLog.Create":{"AccessRules":{"AllowedRoles":[],"AllowedUsers":[],"DeniedUsers":[]},"CachePolicy":{"CacheLevel":"None","AbsoluteExpirationSeconds":0},"LogPolicy":"TrimInputs"},"DefaultRepo.BaseActivityLog.ReadByKey":{"AccessRules":{"AllowedRoles":[],"AllowedUsers":[],"DeniedUsers":[]},"CachePolicy":{"CacheLevel":"None","AbsoluteExpirationSeconds":0},"LogPolicy":"IgnoreLogging"},"DefaultRepo.BaseActivityLog.UpdateByKey":{"AccessRules":{"AllowedRoles":[],"AllowedUsers":[],"DeniedUsers":[]},"CachePolicy":{"CacheLevel":"None","AbsoluteExpirationSeconds":0},"LogPolicy":"TrimInputs"},"DefaultRepo.BaseActivityLog.Delete":{"AccessRules":{"AllowedRoles":[],"AllowedUsers":[],"DeniedUsers":[]},"CachePolicy":{"CacheLevel":"None","AbsoluteExpirationSeconds":0},"LogPolicy":"TrimInputs"},"DefaultRepo.BaseActivityLog.DeleteByKey":{"AccessRules":{"AllowedRoles":[],"AllowedUsers":[],"DeniedUsers":[]},"CachePolicy":{"CacheLevel":"None","AbsoluteExpirationSeconds":0},"LogPolicy":"TrimInputs"}}